{
  "top_category": [
    {
      "id": 1,
      "title": "Овощи и фрукты"
    },
    {
      "id": 2,
      "title": "Бакалеи"
    },
    {
      "id": 3,
      "title": "Хлеб и выпечка"
    },
    {
      "id": 4,
      "title": "Правильное питание"
    },
    {
      "id": 5,
      "title": "Молочная продукция"
    },
    {
      "id": 6,
      "title": "Мясо, курица и рыба"
    }
  ],
  "strike_price": [
    {
      "id": 1,
      "name": "Ламбер",
      "discount": "15%",
      "weight": "2кг",
      "price": 1200,
      "disc_price": 1000
    },
    {
      "id": 2,
      "name": "Свиные ребра",
      "discount": "25%",
      "weight": "1.4кг",
      "price": 800,
      "disc_price": 500
    },
    {
      "id": 3,
      "name": "Стейк из говядины",
      "discount": "20%",
      "weight": "9кг",
      "price": 3000,
      "disc_price": 2500
    },
    {
      "id": 4,
      "name": "Баранина",
      "discount": "15%",
      "weight": "12кг",
      "price": 2800,
      "disc_price": 2300
    }
  ],
  "sale": [
    {
      "id": 1,
      "discount": "до 30%",
      "title": "Весь июнь скидки на продукцию Makfa"
    },
    {
      "id": 2,
      "discount": "до 60%",
      "title": "Купи сейчас или мы купим вас"
    }
  ],
  "cooking": [
    {
      "id": 1,
      "name": "Цезарь с креветками",
      "discount": "15%",
      "weight": "100г",
      "price": 34,
      "disc_price": 45
    },
    {
      "id": 2,
      "name": "Цезарь с курицей",
      "discount": "15%",
      "weight": "2кг",
      "price": 64,
      "disc_price": 75
    }
  ],
  "event": [
  	{
  	  "img": "https://infoeda.com/wp-content/uploads/2018/08/Klassicheskiy_salat_Cezar_s_kuricey.jpg",
  	},
  	{
  	  "img": "https://img.povar.ru/main/31/75/56/ac/salat_quotcezarquot_s_jarenimi_krevetkami-412181.jpeg",
  	},
  	{
  	  "img": "https://www.gastronom.ru/binfiles/images/20160225/b764ea56.jpg",
  	},
  	{
  	  "img": "https://infoeda.com/wp-content/uploads/2017/09/Kak_pozharit_steik_iz_govyadiny.jpg",
  	},
  	{
  	  "img": "https://kakvarim.ru/wp-content/uploads/2019/12/kak-varit-svinye-rebra-post.jpg",
  	},
  	{
  	  "img": "https://cheesewiki.ru/wp-content/uploads/2019/11/lamber-3.jpg",
  	},
  	{
  	  "img": "https://pw.artfile.me/wallpaper/30-01-2017/590x470/eda-raznoe-yagody-frukty-myaso-ovoschi-k-1125053.jpg",
  	},
  	{
  	  "img": "https://www.profiz.ru/upl/5b25597c6750b.jpg",
  	},
  	{
  	  "img": "https://gkgazeta.ru/wp-content/uploads/2019/05/b2ap3_large_kak-vosstanovit-zdorove-pravilnoe-pitanie.jpg",
  	},
  	{
  	  "img": "https://image.freepik.com/free-photo/fruits-and-vegetables_1112-314.jpg",
  	},
  	{
  	  "img": "https://sc02.alicdn.com/kf/ULB8KKftrHnJXKJkSahGq6xhzFXaT.jpg_350x350.jpg",
  	},
  	{
  	  "img": "https://volsklife.ru/wp-content/uploads/2020/04/Hleb.jpg"
  	}
  ]
}
